drf_confidential/__init__.py
drf_confidential/mixins.py
drf_confidential/permissions.py
drf_confidential-1.0.1.dist-info/LICENSE
drf_confidential-1.0.1.dist-info/WHEEL
drf_confidential-1.0.1.dist-info/METADATA
drf_confidential-1.0.1.dist-info/RECORD
