Metadata-Version: 2.1
Name: drf-confidential
Version: 1.0.1
Summary: Handle sensitive fields for django rest framework
Home-page: https://github.com/resurrexi/drf-confidential
License: MIT
Author: Liquan Yang
Author-email: yang.liquan87@gmail.com
Requires-Python: >=3.7,<4.0
Classifier: Framework :: Django
Classifier: License :: OSI Approved :: MIT License
Classifier: Programming Language :: Python :: 3
Classifier: Programming Language :: Python :: 3.7
Classifier: Programming Language :: Python :: 3.8
Classifier: Programming Language :: Python :: 3.9
Classifier: Topic :: Software Development :: Libraries :: Python Modules
Requires-Dist: django (<3.0)
Requires-Dist: djangorestframework (>=3.11.0,<4.0.0)
Project-URL: Repository, https://github.com/resurrexi/drf-confidential
